interacticore/__init__.py
interacticore/commands/__init__.py
interacticore/commands/chatcommand.py
interacticore/commands/llmcommand.py
interacticore/interacticore.py
interacticore/parsers/__init__.py
interacticore/parsers/brokenjsonparser.py
interacticore/utils.py
interacticore-0.0.4.dist-info/LICENSE
interacticore-0.0.4.dist-info/METADATA
interacticore-0.0.4.dist-info/WHEEL
interacticore-0.0.4.dist-info/RECORD
