Metadata-Version: 2.1
Name: interacticore
Version: 0.0.4
Summary: Python module for simplifying common patterns and class for interactgen-py, interactovery-py, and interactilogue-py modules.
Home-page: https://github.com/sitinc/interacticore-py
License: MIT
Author: Justin Randall
Author-email: justin@sitinc.net
Requires-Python: >=3.11,<3.13
Classifier: License :: OSI Approved :: MIT License
Classifier: Programming Language :: Python :: 3
Classifier: Programming Language :: Python :: 3.11
Classifier: Programming Language :: Python :: 3.12
Requires-Dist: langchain-core (>=0.1.25,<0.2.0)
Project-URL: Documentation, https://github.com/sitinc/interacticore-py
Project-URL: Repository, https://github.com/sitinc/interacticore-py
